dragala/__init__.py
dragala/__main__.py
dragala/llm.py
dragala/utils.py
dragala-0.1.0.dist-info/LICENSE
dragala-0.1.0.dist-info/METADATA
dragala-0.1.0.dist-info/WHEEL
dragala-0.1.0.dist-info/entry_points.txt
dragala-0.1.0.dist-info/RECORD
