Metadata-Version: 2.1
Name: dragala
Version: 0.1.0
Summary: dragala - Imagine an AI assistant that speaks Python, taking your natural language requests and turning them into instant, executable scripts. That's the power of dragala, an open-source command-line tool designed to supercharge your productivity and automate repetitive tasks.
Author: An Pham
Author-email: ancs21.ps@gmail.com
Requires-Python: >=3.9,<4.0
Classifier: Programming Language :: Python :: 3
Classifier: Programming Language :: Python :: 3.9
Classifier: Programming Language :: Python :: 3.10
Classifier: Programming Language :: Python :: 3.11
Classifier: Programming Language :: Python :: 3.12
Requires-Dist: google-generativeai (>=0.3.2,<0.4.0)
Requires-Dist: pyyaml (>=6.0.1,<7.0.0)
